lut.v
module pseudo_color_lut (
    input wire [7:0] raw_temp,
    output reg [7:0] r= 8'b0,
    output reg [7:0] g = 8'b0,
    output reg [7:0] b = 8'b0
);
always @(*) begin
    if (raw_temp < 8'd64) begin
        r = 0;
        g = raw_temp << 2;
        b = 255;
    end
    else if (raw_temp < 8'd128) begin
        r = (raw_temp - 64) << 2;
        g = 255;
        b = 255 - ((raw_temp - 64) << 2);
    end
    else if (raw_temp < 8'd192) begin
        r = 255;
        g = 255;
        b = 0;
        g = 255 - ((raw_temp - 128) << 2);
    end
    else begin
        r = 255;
        g = 0;
        b = (raw_temp - 192) << 2;
    end
end
endmodule

sensor.v
module mock_thermal_sensor (
    input wire sclk,
    input wire cs_n,
    input wire mosi,
    output reg miso = 1'b0
);
    reg [7:0] memory_matrix [0:255];
    reg [7:0] shift_reg;
    reg [7:0] rwb_addr;
    reg [4:0] bit_idx;
    initial begin
	 $readmemh("image.hex", memory_matrix);
    end
    always @(posedge sclk or posedge cs_n) begin
    if (cs_n) begin
        bit_idx  <= 0;
        miso     <= 1'b0;
        rwb_addr <= 0;
        shift_reg<= 0;
    end
    else begin

        if (bit_idx < 9) begin

            rwb_addr <= {rwb_addr[6:0], mosi};

            if (bit_idx == 8) begin
		$display("SLAVE ADDR=%02h DATA=%02h",{rwb_addr[6:0], mosi},memory_matrix[{rwb_addr[6:0], mosi}]);
                shift_reg <= memory_matrix[{rwb_addr[6:0], mosi}];
            end

            miso <= 1'b0;
        end
        else begin

            miso <= shift_reg[7];
            shift_reg <= {shift_reg[6:0],1'b0};

        end

        bit_idx <= bit_idx + 1;
    end
end
endmodule

spi_master.v
module spi_master #(
    parameter size = 17,
    parameter mode = 0
) (
    input wire clk,
    input wire en,
    input wire rst,
    input wire tx_en,
    input wire rx_en,
    input wire miso,
    input wire [7:0] address,
    input wire [7:0] data_out,
    output reg sclk,
    output reg cs_n,
    output reg mosi,
    output reg [15:0] data_in,
    output reg rx_valid
);
    reg [7:0] count;
    reg [7:0] bit_count;
    reg [15:0] tx_data;
    reg [7:0] rx_data;
    localparam LIMIT = 8'd1;
    localparam FINAL = size;
    reg tx_en_reg;
    reg rx_en_reg;
    reg is_write;
    reg CPOL, CPHA;

    always @(posedge clk) begin
        if (rst) begin
            count     <= 0;
            bit_count <= 0;
            mosi      <= 1'b0;
            tx_data   <= 0;
            rx_data   <= 0;
            data_in   <= 0;
            tx_en_reg <= 0;
            rx_en_reg <= 0;
            rx_valid  <= 0;
            is_write  <= 0;
            cs_n      <= 1'b1;
            if (mode == 0) begin CPOL <= 0; CPHA <= 0; sclk <= 0; end
            else if (mode == 1) begin CPOL <= 0; CPHA <= 1; sclk <= 0; end
            else if (mode == 2) begin CPOL <= 1; CPHA <= 0; sclk <= 1; end
            else begin CPOL <= 1; CPHA <= 1; sclk <= 1; end
        end else begin
            tx_en_reg <= tx_en;
            rx_en_reg <= rx_en;
            rx_valid  <= 1'b0;
            if (en) begin
                if (cs_n) begin
                    if (tx_en_reg && !tx_en) begin
                        cs_n      <= 1'b0;
                        bit_count <= 0;
                        count     <= 0;
                        sclk      <= CPOL;
                        is_write  <= 1'b1;
                        tx_data   <= {address, data_out};
                        mosi      <= 1'b1; 
                    end else if (rx_en_reg && !rx_en) begin
                        cs_n      <= 1'b0;
                        bit_count <= 0;
                        count     <= 0;
                        sclk      <= CPOL;
                        is_write  <= 1'b0;
                        tx_data   <= {address, 8'b0};
                        mosi      <= 1'b0;
	                rx_data   <= 8'd0; 
                    end
                end else begin
                    if (count == LIMIT) begin
                        count <= 0;
                        sclk  <= ~sclk;
                        if (~sclk != CPOL) begin
                            if (!is_write && (bit_count >= 9) && (bit_count < FINAL)) begin
                               
                               rx_data <= {rx_data[6:0], miso};
                             
                            end
                            bit_count <= bit_count + 1;
                        end else begin
                            if (bit_count < FINAL) begin
                                if (!is_write && (bit_count >= 9)) begin
                                    mosi <= 1'b0;
                                end else begin
                                    mosi    <= tx_data[15];
                                    tx_data <= {tx_data[14:0], 1'b0};
                                end
                            end else begin
                                cs_n     <= 1'b1;
                                mosi     <= 1'b0;
                                sclk     <= CPOL;
                                if (!is_write) begin
                                    data_in  <={8'b0, rx_data};
				$display("ADDR=%02h RECEIVED=%02h TIME=%0t",address,{rx_data[6:0], miso},$time);
                                    rx_valid <= 1'b1;
                                end
                            end
                        end
                    end else begin
                        count <= count + 1;
                    end
                end
            end else begin
                cs_n <= 1'b1;
                sclk <= CPOL;
                mosi <= 1'b0;
            end
        end
    end
endmodule

tb_final.v
module tb_thermal();
    reg clk, en, tx_en, rx_en, rst;
    reg [7:0] address;
    reg [7:0] data_out;
    wire sclk, cs_n, mosi, miso, rx_valid;
    wire [15:0] data_in;

    wire [7:0] r_wire, g_wire, b_wire;
    reg [7:0] image_ram_r [0:255];
    reg [7:0] image_ram_g [0:255];
    reg [7:0] image_ram_b [0:255];

    integer ppm_file = 0;
    integer i;

   
    spi_master #(.size(17), .mode(0)) master_inst (
        .clk(clk), .en(en), .rst(rst), .tx_en(tx_en), .rx_en(rx_en),
        .miso(miso), .address(address), .data_out(data_out),
        .sclk(sclk), .cs_n(cs_n), .mosi(mosi), .data_in(data_in), .rx_valid(rx_valid)
    );

   
    mock_thermal_sensor sensor_inst (
        .sclk(sclk), .cs_n(cs_n), .mosi(mosi), .miso(miso)
    );

   
    pseudo_color_lut lut_inst (
        .raw_temp(data_in[7:0]),
        .r(r_wire), .g(g_wire), .b(b_wire)
    );

   
    initial clk = 0;
    always #5 clk = ~clk;

    initial begin
        $dumpfile("thermal.vcd");
        $dumpvars(0, tb_thermal);

   
        rst = 1; en = 0; tx_en = 0; rx_en = 0; address = 0; data_out = 0; #40;
        rst = 0; en = 1;#40;

   
        for (i = 0; i < 256; i = i + 1) begin
            address = i;
            rx_en = 1; #20; 
            rx_en = 0; 
            $display("addr=%0d temp=%h", i, data_in[7:0]);
            @(posedge rx_valid);#1;
   
            image_ram_r[i] = r_wire;
            image_ram_g[i] = g_wire;
            image_ram_b[i] = b_wire;
            #40;
        end

	ppm_file = $fopen("thermal_output.ppm", "w");
        if (ppm_file == 0) begin
            $display("Error: Failed to clear storage nodes for output target allocation.");
            $finish;
        end

	
        $fwrite(ppm_file, "P3\n");
        $fwrite(ppm_file, "16 16\n");
        $fwrite(ppm_file, "255\n");

        
        for (i = 0; i < 256; i = i + 1) begin
            $fwrite(ppm_file, "%d %d %d\n", image_ram_r[i], image_ram_g[i], image_ram_b[i]);
        end

        $fclose(ppm_file);
        $display("Success: 'thermal_output.ppm' successfully written into directory layer.");
        #20;
        $finish;
    end
endmodule

thermal.vcd
$date
	Wed Jun 24 10:45:28 2026
$end
$version
	Icarus Verilog
$end
$timescale
	1s
$end
$scope module tb_thermal $end
$var wire 1 ! sclk $end
$var wire 1 " rx_valid $end
$var wire 8 # r_wire [7:0] $end
$var wire 1 $ mosi $end
$var wire 1 % miso $end
$var wire 8 & g_wire [7:0] $end
$var wire 16 ' data_in [15:0] $end
$var wire 1 ( cs_n $end
$var wire 8 ) b_wire [7:0] $end
$var reg 8 * address [7:0] $end
$var reg 1 + clk $end
$var reg 8 , data_out [7:0] $end
$var reg 1 - en $end
$var reg 1 . rst $end
$var reg 1 / rx_en $end
$var reg 1 0 tx_en $end
$var integer 32 1 i [31:0] $end
$var integer 32 2 ppm_file [31:0] $end
$scope module lut_inst $end
$var wire 8 3 raw_temp [7:0] $end
$var reg 8 4 b [7:0] $end
$var reg 8 5 g [7:0] $end
$var reg 8 6 r [7:0] $end
$upscope $end
$scope module master_inst $end
$var wire 8 7 address [7:0] $end
$var wire 1 + clk $end
$var wire 8 8 data_out [7:0] $end
$var wire 1 - en $end
$var wire 1 . rst $end
$var wire 1 / rx_en $end
$var wire 1 0 tx_en $end
$var wire 1 % miso $end
$var reg 1 9 CPHA $end
$var reg 1 : CPOL $end
$var reg 8 ; bit_count [7:0] $end
$var reg 8 < count [7:0] $end
$var reg 1 ( cs_n $end
$var reg 16 = data_in [15:0] $end
$var reg 1 > is_write $end
$var reg 1 $ mosi $end
$var reg 8 ? rx_data [7:0] $end
$var reg 1 @ rx_en_reg $end
$var reg 1 " rx_valid $end
$var reg 1 ! sclk $end
$var reg 16 A tx_data [15:0] $end
$var reg 1 B tx_en_reg $end
$upscope $end
$scope module sensor_inst $end
$var wire 1 ( cs_n $end
$var wire 1 $ mosi $end
$var wire 1 ! sclk $end
$var reg 5 C bit_idx [4:0] $end
$var reg 1 % miso $end
$var reg 8 D rwb_addr [7:0] $end
$var reg 8 E shift_reg [7:0] $end
$upscope $end
$upscope $end
$enddefinitions $end
#0
$dumpvars
bx E
bx D
bx C
xB
bx A
x@
bx ?
x>
bx =
bx <
bx ;
x:
x9
b0 8
b0 7
b0 6
b0 5
b0 4
bx 3
b0 2
bx 1
00
0/
1.
0-
b0 ,
0+
b0 *
b0 )
x(
bx '
b0 &
0%
x$
b0 #
x"
x!
$end
#5
b0 E
b0 D
b0 C
b11111111 )
b11111111 4
b0 3
0!
09
0:
1(
0>
0"
0@
0B
b0 '
b0 =
b0 ?
b0 A
0$
b0 ;
b0 <
1+
#10
0+
#15
1+
#20
0+
#25
1+
#30
0+
#35
1+
#40
0+
1-
0.
#45
1+
#50
0+
#55
1+
#60
0+
#65
1+
#70
0+
#75
1+
#80
0+
1/
b0 1
#85
1@
1+
#90
0+
#95
1+
#100
0+
0/
#105
0(
0@
1+
#110
0+
#115
b1 <
1+
#120
0+
#125
b1 C
b1 ;
1!
b0 <
1+
#130
0+
#135
b1 <
1+
#140
0+
#145
0!
b0 <
1+
#150
0+
#155
b1 <
1+
#160
0+
#165
b10 C
b10 ;
1!
b0 <
1+
#170
0+
#175
b1 <
1+
#180
0+
#185
0!
b0 <
1+
#190
0+
#195
b1 <
1+
#200
0+
#205
b11 C
b11 ;
1!
b0 <
1+
#210
0+
#215
b1 <
1+
#220
0+
#225
0!
b0 <
1+
#230
0+
#235
b1 <
1+
#240
0+
#245
b100 C
b100 ;
1!
b0 <
1+
#250
0+
#255
b1 <
1+
#260
0+
#265
0!
b0 <
1+
#270
0+
#275
b1 <
1+
#280
0+
#285
b101 C
b101 ;
1!
b0 <
1+
#290
0+
#295
b1 <
1+
#300
0+
#305
0!
b0 <
1+
#310
0+
#315
b1 <
1+
#320
0+
#325
b110 C
b110 ;
1!
b0 <
1+
#330
0+
#335
b1 <
1+
#340
0+
#345
0!
b0 <
1+
#350
0+
#355
b1 <
1+
#360
0+
#365
b111 C
b111 ;
1!
b0 <
1+
#370
0+
#375
b1 <
1+
#380
0+
#385
0!
b0 <
1+
#390
0+
#395
b1 <
1+
#400
0+
#405
b1000 C
b1000 ;
1!
b0 <
1+
#410
0+
#415
b1 <
1+
#420
0+
#425
0!
b0 <
1+
#430
0+
#435
b1 <
1+
#440
0+
#445
b1001 C
b1 E
b1001 ;
1!
b0 <
1+
#450
0+
#455
b1 <
1+
#460
0+
#465
0!
b0 <
1+
#470
0+
#475
b1 <
1+
#480
0+
#485
b1010 C
b10 E
b1010 ;
1!
b0 <
1+
#490
0+
#495
b1 <
1+
#500
0+
#505
0!
b0 <
1+
#510
0+
#515
b1 <
1+
#520
0+
#525
b1011 C
b100 E
b1011 ;
1!
b0 <
1+
#530
0+
#535
b1 <
1+
#540
0+
#545
0!
b0 <
1+
#550
0+
#555
b1 <
1+
#560
0+
#565
b1100 C
b1000 E
b1100 ;
1!
b0 <
1+
#570
0+
#575
b1 <
1+
#580
0+
#585
0!
b0 <
1+
#590
0+
#595
b1 <
1+
#600
0+
#605
b1101 C
b10000 E
b1101 ;
1!
b0 <
1+
#610
0+
#615
b1 <
1+
#620
0+
#625
0!
b0 <
1+
#630
0+
#635
b1 <
1+
#640
0+
#645
b1110 C
b100000 E
b1110 ;
1!
b0 <
1+
#650
0+
#655
b1 <
1+
#660
0+
#665
0!
b0 <
1+
#670
0+
#675
b1 <
1+
#680
0+
#685
b1111 C
b1000000 E
b1111 ;
1!
b0 <
1+
#690
0+
#695
b1 <
1+
#700
0+
#705
0!
b0 <
1+
#710
0+
#715
b1 <
1+
#720
0+
#725
b10000 C
b10000000 E
b10000 ;
1!
b0 <
1+
#730
0+
#735
b1 <
1+
#740
0+
#745
0!
b0 <
1+
#750
0+
#755
b1 <
1+
#760
0+
#765
b10001 C
b0 E
1%
b10001 ;
1!
b0 <
1+
#770
0+
#775
b1 <
1+
#780
0+
#785
0%
b0 C
1"
1(
0!
b0 <
1+
#790
0+
#795
0"
1+
#800
0+
#805
1+
#810
0+
#815
1+
#820
0+
#825
1+
#826
1/
b1 *
b1 7
b1 1
#830
0+
#835
1@
1+
#840
0+
#845
1+
#846
0/
#850
0+
#855
b100000000 A
b0 ;
0(
0@
1+
#860
0+
#865
b1 <
1+
#870
0+
#875
b1 C
b1 ;
1!
b0 <
1+
#880
0+
#885
b1 <
1+
#890
0+
#895
b1000000000 A
0!
b0 <
1+
#900
0+
#905
b1 <
1+
#910
0+
#915
b10 C
b10 ;
1!
b0 <
1+
#920
0+
#925
b1 <
1+
#930
0+
#935
b10000000000 A
0!
b0 <
1+
#940
0+
#945
b1 <
1+
#950
0+
#955
b11 C
b11 ;
1!
b0 <
1+
#960
0+
#965
b1 <
1+
#970
0+
#975
b100000000000 A
0!
b0 <
1+
#980
0+
#985
b1 <
1+
#990
0+
#995
b100 C
b100 ;
1!
b0 <
1+
#1000
0+
#1005
b1 <
1+
#1010
0+
#1015
b1000000000000 A
0!
b0 <
1+
#1020
0+
#1025
b1 <
1+
#1030
0+
#1035
b101 C
b101 ;
1!
b0 <
1+
#1040
0+
#1045
b1 <
1+
#1050
0+
#1055
b10000000000000 A
0!
b0 <
1+
#1060
0+
#1065
b1 <
1+
#1070
0+
#1075
b110 C
b110 ;
1!
b0 <
1+
#1080
0+
#1085
b1 <
1+
#1090
0+
#1095
b100000000000000 A
0!
b0 <
1+
#1100
0+
#1105
b1 <
1+
#1110
0+
#1115
b111 C
b111 ;
1!
b0 <
1+
#1120
0+
#1125
b1 <
1+
#1130
0+
#1135
b1000000000000000 A
0!
b0 <
1+
#1140
0+
#1145
b1 <
1+
#1150
0+
#1155
b1000 C
b1000 ;
1!
b0 <
1+
#1160
0+
#1165
b1 <
1+
#1170
0+
#1175
b0 A
1$
0!
b0 <
1+
#1180
0+
#1185
b1 <
1+
#1190
0+
#1195
b1001 C
b11 E
b1 D
b1001 ;
1!
b0 <
1+
#1200
0+
#1205
b1 <
1+
#1210
0+
#1215
0$
0!
b0 <
1+
#1220
0+
#1225
b1 <
1+
#1230
0+
#1235
b1010 C
b110 E
b1010 ;
1!
b0 <
1+
#1240
0+
#1245
b1 <
1+
#1250
0+
#1255
0!
b0 <
1+
#1260
0+
#1265
b1 <
1+
#1270
0+
#1275
b1011 C
b1100 E
b1011 ;
1!
b0 <
1+
#1280
0+
#1285
b1 <
1+
#1290
0+
#1295
0!
b0 <
1+
#1300
0+
#1305
b1 <
1+
#1310
0+
#1315
b1100 C
b11000 E
b1100 ;
1!
b0 <
1+
#1320
0+
#1325
b1 <
1+
#1330
0+
#1335
0!
b0 <
1+
#1340
0+
#1345
b1 <
1+
#1350
0+
#1355
b1101 C
b110000 E
b1101 ;
1!
b0 <
1+
#1360
0+
#1365
b1 <
1+
#1370
0+
#1375
0!
b0 <
1+
#1380
0+
#1385
b1 <
1+
#1390
0+
#1395
b1110 C
b1100000 E
b1110 ;
1!
b0 <
1+
#1400
0+
#1405
b1 <
1+
#1410
0+
#1415
0!
b0 <
1+
#1420
0+
#1425
b1 <
1+
#1430
0+
#1435
b1111 C
b11000000 E
b1111 ;
1!
b0 <
1+
#1440
0+
#1445
b1 <
1+
#1450
0+
#1455
0!
b0 <
1+
#1460
0+
#1465
b1 <
1+
#1470
0+
#1475
b10000 C
b10000000 E
1%
b10000 ;
1!
b0 <
1+
#1480
0+
#1485
b1 <
1+
#1490
0+
#1495
0!
b0 <
1+
#1500
0+
#1505
b1 <
1+
#1510
0+
#1515
b10001 C
b0 E
b10001 ;
b1 ?
1!
b0 <
1+
#1520
0+
#1525
b1 <
1+
#1530
0+
#1535
b0 D
0%
b0 C
b100 &
b100 5
b1 3
1"
b1 '
b1 =
1(
0!
b0 <
1+
#1540
0+
#1545
0"
1+
#1550
0+
#1555
1+
#1560
0+
#1565
1+
#1570
0+
#1575
1+
#1576
1/
b10 *
b10 7
b10 1
#1580
0+
#1585
1@
1+
#1590
0+
#1595
1+
#1596
0/
#1600
0+
#1605
b0 ?
b1000000000 A
b0 ;
0(
0@
1+
#1610
0+
#1615
b1 <
1+
#1620
0+
#1625
b1 C
b1 ;
1!
b0 <
1+
#1630
0+
#1635
b1 <
1+
#1640
0+
#1645
b10000000000 A
0!
b0 <
1+
#1650
0+
#1655
b1 <
1+
#1660
0+
#1665
b10 C
b10 ;
1!
b0 <
1+
#1670
0+
#1675
b1 <
1+
#1680
0+
#1685
b100000000000 A
0!
b0 <
1+
#1690
0+
#1695
b1 <
1+
#1700
0+
#1705
b11 C
b11 ;
1!
b0 <
1+
#1710
0+
#1715
b1 <
1+
#1720
0+
#1725
b1000000000000 A
0!
b0 <
1+
#1730
0+
#1735
b1 <
1+
#1740
0+
#1745
b100 C
b100 ;
1!
b0 <
1+
#1750
0+
#1755
b1 <
1+
#1760
0+
#1765
b10000000000000 A
0!
b0 <
1+
#1770
0+
#1775
b1 <
1+
#1780
0+
#1785
b101 C
b101 ;
1!
b0 <
1+
#1790
0+
#1795
b1 <
1+
#1800
0+
#1805
b100000000000000 A
0!
b0 <
1+
#1810
0+
#1815
b1 <
1+
#1820
0+
#1825
b110 C
b110 ;
1!
b0 <
1+
#1830
0+
#1835
b1 <
1+
#1840
0+
#1845
b1000000000000000 A
0!
b0 <
1+
#1850
0+
#1855
b1 <
1+
#1860
0+
#1865
b111 C
b111 ;
1!
b0 <
1+
#1870
0+
#1875
b1 <
1+
#1880
0+
#1885
b0 A
1$
0!
b0 <
1+
#1890
0+
#1895
b1 <
1+
#1900
0+
#1905
b1000 C
b1 D
b1000 ;
1!
b0 <
1+
#1910
0+
#1915
b1 <
1+
#1920
0+
#1925
0$
0!
b0 <
1+
#1930
0+
#1935
b1 <
1+
#1940
0+
#1945
b1001 C
b110 E
b10 D
b1001 ;
1!
b0 <
1+
#1950
0+
#1955
b1 <
1+
#1960
0+
#1965
0!
b0 <
1+
#1970
0+
#1975
b1 <
1+
#1980
0+
#1985
b1010 C
b1100 E
b1010 ;
1!
b0 <
1+
#1990
0+
#1995
b1 <
1+
#2000
0+
#2005
0!
b0 <
1+
#2010
0+
#2015
b1 <
1+
#2020
0+
#2025
b1011 C
b11000 E
b1011 ;
1!
b0 <
1+
#2030
0+
#2035
b1 <
1+
#2040
0+
#2045
0!
b0 <
1+
#2050
0+
#2055
b1 <
1+
#2060
0+
#2065
b1100 C
b110000 E
b1100 ;
1!
b0 <
1+
#2070
0+
#2075
b1 <
1+
#2080
0+
#2085
0!
b0 <
1+
#2090
0+
#2095
b1 <
1+
#2100
0+
#2105
b1101 C
b1100000 E
b1101 ;
1!
b0 <
1+
#2110
0+
#2115
b1 <
1+
#2120
0+
#2125
0!
b0 <
1+
#2130
0+
#2135
b1 <
1+
#2140
0+
#2145
b1110 C
b11000000 E
b1110 ;
1!
b0 <
1+
#2150
0+
#2155
b1 <
1+
#2160
0+
#2165
0!
b0 <
1+
#2170
0+
#2175
b1 <
1+
#2180
0+
#2185
b1111 C
b10000000 E
1%
b1111 ;
1!
b0 <
1+
#2190
0+
#2195
b1 <
1+
#2200
0+
#2205
0!
b0 <
1+
#2210
0+
#2215
b1 <
1+
#2220
0+
#2225
b10000 C
b0 E
b10000 ;
b1 ?
1!
b0 <
1+
#2230
0+
#2235
b1 <
1+
#2240
0+
#2245
0!
b0 <
1+
#2250
0+
#2255
b1 <
1+
#2260
0+
#2265
b10001 C
0%
b10001 ;
b11 ?
1!
b0 <
1+
#2270
0+
#2275
b1 <
1+
#2280
0+
#2285
b0 D
b0 C
b1100 &
b1100 5
b11 3
1"
b11 '
b11 =
1(
0!
b0 <
1+
#2290
0+
#2295
0"
1+
#2300
0+
#2305
1+
#2310
0+
#2315
1+
#2320
0+
#2325
1+
#2326
1/
b11 *
b11 7
b11 1
#2330
0+
#2335
1@
1+
#2340
0+
#2345
1+
#2346
0/
#2350
0+
#2355
b0 ?
b1100000000 A
b0 ;
0(
0@
1+
#2360
0+
#2365
b1 <
1+
#2370
0+
#2375
b1 C
b1 ;
1!
b0 <
1+
#2380
0+
#2385
b1 <
1+
#2390
0+
#2395
b11000000000 A
0!
b0 <
1+
#2400
0+
#2405
b1 <
1+
#2410
0+
#2415
b10 C
b10 ;
1!
b0 <
1+
#2420
0+
#2425
b1 <
1+
#2430
0+
#2435
b110000000000 A
0!
b0 <
1+
#2440
0+
#2445
b1 <
1+
#2450
0+
#2455
b11 C
b11 ;
1!
b0 <
1+
#2460
0+
#2465
b1 <
1+
#2470
0+
#2475
b1100000000000 A
0!
b0 <
1+
#2480
0+
#2485
b1 <
1+
#2490
0+
#2495
b100 C
b100 ;
1!
b0 <
1+
#2500
0+
#2505
b1 <
1+
#2510
0+
#2515
b11000000000000 A
0!
b0 <
1+
#2520
0+
#2525
b1 <
1+
#2530
0+
#2535
b101 C
b101 ;
1!
b0 <
1+
#2540
0+
#2545
b1 <
1+
#2550
0+
#2555
b110000000000000 A
0!
b0 <
1+
#2560
0+
#2565
b1 <
1+
#2570
0+
#2575
b110 C
b110 ;
1!
b0 <
1+
#2580
0+
#2585
b1 <
1+
#2590
0+
#2595
b1100000000000000 A
0!
b0 <
1+
#2600
0+
#2605
b1 <
1+
#2610
0+
#2615
b111 C
b111 ;
1!
b0 <
1+
#2620
0+
#2625
b1 <
1+
#2630
0+
#2635
b1000000000000000 A
1$
0!
b0 <
1+
#2640
0+
#2645
b1 <
1+
#2650
0+
#2655
b1000 C
b1 D
b1000 ;
1!
b0 <
1+
#2660
0+
#2665
b1 <
1+
#2670
0+
#2675
b0 A
0!
b0 <
1+
#2680
0+
#2685
b1 <
1+
#2690
0+
#2695
b1001 C
b1010 E
b11 D
b1001 ;
1!
b0 <
1+
#2700
0+
#2705
b1 <
1+
#2710
0+
#2715
0$
0!
b0 <
1+
#2720
0+
#2725
b1 <
1+
#2730
0+
#2735
b1010 C
b10100 E
b1010 ;
1!
b0 <
1+
#2740
0+
#2745
b1 <
1+
#2750
0+
#2755
0!
b0 <
1+
#2760
0+
#2765
b1 <
1+
#2770
0+
#2775
b1011 C
b101000 E
b1011 ;
1!
b0 <
1+
#2780
0+
#2785
b1 <
1+
#2790
0+
#2795
0!
b0 <
1+
#2800
0+
#2805
b1 <
1+
#2810
0+
#2815
b1100 C
b1010000 E
b1100 ;
1!
b0 <
1+
#2820
0+
#2825
b1 <
1+
#2830
0+
#2835
0!
b0 <
1+
#2840
0+
#2845
b1 <
1+
#2850
0+
#2855
b1101 C
b10100000 E
b1101 ;
1!
b0 <
1+
#2860
0+
#2865
b1 <
1+
#2870
0+
#2875
0!
b0 <
1+
#2880
0+
#2885
b1 <
1+
#2890
0+
#2895
b1110 C
b1000000 E
1%
b1110 ;
1!
b0 <
1+
#2900
0+
#2905
b1 <
1+
#2910
0+
#2915
0!
b0 <
1+
#2920
0+
#2925
b1 <
1+
#2930
0+
#2935
b1111 C
b10000000 E
0%
b1111 ;
b1 ?
1!
b0 <
1+
#2940
0+
#2945
b1 <
1+
#2950
0+
#2955
0!
b0 <
1+
#2960
0+
#2965
b1 <
1+
#2970
0+
#2975
b10000 C
b0 E
1%
b10000 ;
b10 ?
1!
b0 <
1+
#2980
0+
#2985
b1 <
1+
#2990
0+
#2995
0!
b0 <
1+
#3000
0+
#3005
b1 <
1+
#3010
0+
#3015
b10001 C
0%
b10001 ;
b101 ?
1!
b0 <
1+
#3020
0+
#3025
b1 <
1+
#3030
0+
#3035
b0 D
b0 C
b10100 &
b10100 5
b101 3
1"
b101 '
b101 =
1(
0!
b0 <
1+
#3040
0+
#3045
0"
1+
#3050
0+
#3055
1+
#3060
0+
#3065
1+
#3070
0+
#3075
1+
#3076
1/
b100 *
b100 7
b100 1
#3080
0+
#3085
1@
1+
#3090
0+
#3095
1+
#3096
0/
#3100
0+
#3105
b0 ?
b10000000000 A
b0 ;
0(
0@
1+
#3110
0+
#3115
b1 <
1+
#3120
0+
#3125
b1 C
b1 ;
1!
b0 <
1+
#3130
0+
#3135
b1 <
1+
#3140
0+
#3145
b100000000000 A
0!
b0 <
1+
#3150
0+
#3155
b1 <
1+
#3160
0+
#3165
b10 C
b10 ;
1!
b0 <
1+
#3170
0+
#3175
b1 <
1+
#3180
0+
#3185
b1000000000000 A
0!
b0 <
1+
#3190
0+
#3195
b1 <
1+
#3200
0+
#3205
b11 C
b11 ;
1!
b0 <
1+
#3210
0+
#3215
b1 <
1+
#3220
0+
#3225
b10000000000000 A
0!
b0 <
1+
#3230
0+
#3235
b1 <
1+
#3240
0+
#3245
b100 C
b100 ;
1!
b0 <
1+
#3250
0+
#3255
b1 <
1+
#3260
0+
#3265
b100000000000000 A
0!
b0 <
1+
#3270
0+
#3275
b1 <
1+
#3280
0+
#3285
b101 C
b101 ;
1!
b0 <
1+
#3290
0+
#3295
b1 <
1+
#3300
0+
#3305
b1000000000000000 A
0!
b0 <
1+
#3310
0+
#3315
b1 <
1+
#3320
0+
#3325
b110 C
b110 ;
1!
b0 <
1+
#3330
0+
#3335
b1 <
1+
#3340
0+
#3345
b0 A
1$
0!
b0 <
1+
#3350
0+
#3355
b1 <
1+
#3360
0+
#3365
b111 C
b1 D
b111 ;
1!
b0 <
1+
#3370
0+
#3375
b1 <
1+
#3380
0+
#3385
0$
0!
b0 <
1+
#3390
0+
#3395
b1 <
1+
#3400
0+
#3405
b1000 C
b10 D
b1000 ;
1!
b0 <
1+
#3410
0+
#3415
b1 <
1+
#3420
0+
#3425
0!
b0 <
1+
#3430
0+
#3435
b1 <
1+
#3440
0+
#3445
b1001 C
b1101 E
b100 D
b1001 ;
1!
b0 <
1+
#3450
0+
#3455
b1 <
1+
#3460
0+
#3465
0!
b0 <
1+
#3470
0+
#3475
b1 <
1+
#3480
0+
#3485
b1010 C
b11010 E
b1010 ;
1!
b0 <
1+
#3490
0+
#3495
b1 <
1+
#3500
0+
#3505
0!
b0 <
1+
#3510
0+
#3515
b1 <
1+
#3520
0+
#3525
b1011 C
b110100 E
b1011 ;
1!
b0 <
1+
#3530
0+
#3535
b1 <
1+
#3540
0+
#3545
0!
b0 <
1+
#3550
0+
#3555
b1 <
1+
#3560
0+
#3565
b1100 C
b1101000 E
b1100 ;
1!
b0 <
1+
#3570
0+
#3575
b1 <
1+
#3580
0+
#3585
0!
b0 <
1+
#3590
0+
#3595
b1 <
1+
#3600
0+
#3605
b1101 C
b11010000 E
b1101 ;
1!
b0 <
1+
#3610
0+
#3615
b1 <
1+
#3620
0+
#3625
0!
b0 <
1+
#3630
0+
#3635
b1 <
1+
#3640
0+
#3645
b1110 C
b10100000 E
1%
b1110 ;
1!
b0 <
1+
#3650
0+
#3655
b1 <
1+
#3660
0+
#3665
0!
b0 <
1+
#3670
0+
#3675
b1 <
1+
#3680
0+
#3685
b1111 C
b1000000 E
b1111 ;
b1 ?
1!
b0 <
1+
#3690
0+
#3695
b1 <
1+
#3700
0+
#3705
0!
b0 <
1+
#3710
0+
#3715
b1 <
1+
#3720
0+
#3725
b10000 C
b10000000 E
0%
b10000 ;
b11 ?
1!
b0 <
1+
#3730
0+
#3735
b1 <
1+
#3740
0+
#3745
0!
b0 <
1+
#3750
0+
#3755
b1 <
1+
#3760
0+
#3765
b10001 C
b0 E
1%
b10001 ;
b110 ?
1!
b0 <
1+
#3770
0+
#3775
b1 <
1+
#3780
0+
#3785
b0 D
0%
b0 C
b11000 &
b11000 5
b110 3
1"
b110 '
b110 =
1(
0!
b0 <
1+
#3790
0+
#3795
0"
1+
#3800
0+
#3805
1+
#3810
0+
#3815
1+
#3820
0+
#3825
1+
#3826
1/
b101 *
b101 7
b101 1
#3830
0+
#3835
1@
1+
#3840
0+
#3845
1+
#3846
0/
#3850
0+
#3855
b0 ?
b10100000000 A
b0 ;
0(
0@
1+
#3860
0+
#3865
b1 <
1+
#3870
0+
#3875
b1 C
b1 ;
1!
b0 <
1+
#3880
0+
#3885
b1 <
1+
#3890
0+
#3895
b101000000000 A
0!
b0 <
1+
#3900
0+
#3905
b1 <
1+
#3910
0+
#3915
b10 C
b10 ;
1!
b0 <
1+
#3920
0+
#3925
b1 <
1+
#3930
0+
#3935
b1010000000000 A
0!
b0 <
1+
#3940
0+
#3945
b1 <
1+
#3950
0+
#3955
b11 C
b11 ;
1!
b0 <
1+
#3960
0+
#3965
b1 <
1+
#3970
0+
#3975
b10100000000000 A
0!
b0 <
1+
#3980
0+
#3985
b1 <
1+
#3990
0+
#3995
b100 C
b100 ;
1!
b0 <
1+
#4000
0+
#4005
b1 <
1+
#4010
0+
#4015
b101000000000000 A
0!
b0 <
1+
#4020
0+
#4025
b1 <
1+
#4030
0+
#4035
b101 C
b101 ;
1!
b0 <
1+
#4040
0+
#4045
b1 <
1+
#4050
0+
#4055
b1010000000000000 A
0!
b0 <
1+
#4060
0+
#4065
b1 <
1+
#4070
0+
#4075
b110 C
b110 ;
1!
b0 <
1+
#4080
0+
#4085
b1 <
1+
#4090
0+
#4095
b100000000000000 A
1$
0!
b0 <
1+
#4100
0+
#4105
b1 <
1+
#4110
0+
#4115
b111 C
b1 D
b111 ;
1!
b0 <
1+
#4120
0+
#4125
b1 <
1+
#4130
0+
#4135
b1000000000000000 A
0$
0!
b0 <
1+
#4140
0+
#4145
b1 <
1+
#4150
0+
#4155
b1000 C
b10 D
b1000 ;
1!
b0 <
1+
#4160
0+
